multiparlog/__init__.py
multiparlog/mplogging.py
multiparlog-1.0.9.dist-info/LICENSE
multiparlog-1.0.9.dist-info/METADATA
multiparlog-1.0.9.dist-info/WHEEL
multiparlog-1.0.9.dist-info/top_level.txt
multiparlog-1.0.9.dist-info/RECORD
