Metadata-Version: 2.1
Name: multiparlog
Version: 1.0.9
Summary: A flexible multi-processing safe logging tool
Author-email: Ralf Kotulla <ralf.kotulla@gmail.com>
Project-URL: Homepage, https://github.com/rkotulla/multiparallel_logging
Project-URL: Bug Tracker, https://github.com/rkotulla/multiparallel_logging/issues
Classifier: Programming Language :: Python :: 3
Classifier: License :: OSI Approved :: MIT License
Classifier: Operating System :: OS Independent
Requires-Python: >=3.6
License-File: LICENSE
